lie_learn/__init__.py
lie_learn/broadcasting.py
lie_learn/spaces/spherical_quadrature.pyx
lie_learn/spaces/spherical_quadrature.c
lie_learn/spaces/S3.py
lie_learn/spaces/__init__.py
lie_learn/spaces/rn.py
lie_learn/spaces/Tn.py
lie_learn/spaces/spherical_quadrature.cpython-39-x86_64-linux-gnu.so
lie_learn/spaces/S2.py
lie_learn/spectral/__init__.py
lie_learn/spectral/SO3FFT_Naive.py
lie_learn/spectral/T2FFT.py
lie_learn/spectral/SE2FFT.py
lie_learn/spectral/T1FFT.py
lie_learn/spectral/PolarFFT.py
lie_learn/spectral/S2FFT_NFFT.py
lie_learn/spectral/fourier_interpolation.py
lie_learn/spectral/SO3_conv.py
lie_learn/spectral/S2_conv.py
lie_learn/spectral/S2FFT.py
lie_learn/spectral/FFTBase.py
lie_learn/groups/__init__.py
lie_learn/groups/SO2.py
lie_learn/groups/SE2.py
lie_learn/groups/SO3.c
lie_learn/groups/SO3.cpython-39-x86_64-linux-gnu.so
lie_learn/groups/SO3_tests.py
lie_learn/groups/SO3.pyx
lie_learn/representations/__init__.py
lie_learn/representations/SO3/clebsch_gordan_numerical.py
lie_learn/representations/SO3/__init__.py
lie_learn/representations/SO3/spherical_harmonics.py
lie_learn/representations/SO3/irrep_bases.pyx
lie_learn/representations/SO3/test_spherical_harmonics.py
lie_learn/representations/SO3/irrep_bases.cpython-39-x86_64-linux-gnu.so
lie_learn/representations/SO3/test_SO3_irrep_bases.py
lie_learn/representations/SO3/wigner_d.py
lie_learn/representations/SO3/indexing.py
lie_learn/representations/SO3/irrep_bases.c
lie_learn/representations/SO3/test_wigner_d.py
lie_learn/representations/SO3/pinchon_hoggan/pinchon_hoggan.cpython-39-x86_64-linux-gnu.so
lie_learn/representations/SO3/pinchon_hoggan/pinchon_hoggan_dense.py
lie_learn/representations/SO3/pinchon_hoggan/__init__.py
lie_learn/representations/SO3/pinchon_hoggan/pinchon_hoggan.c
lie_learn/representations/SO3/pinchon_hoggan/J_dense_0-150.npy
lie_learn/representations/SO3/pinchon_hoggan/J_block_0-150.npy
lie_learn-0.0.2.dist-info/LICENSE
lie_learn-0.0.2.dist-info/WHEEL
lie_learn-0.0.2.dist-info/top_level.txt
lie_learn-0.0.2.dist-info/RECORD
lie_learn-0.0.2.dist-info/METADATA
